papyrus_scripts/__init__.py
papyrus_scripts/__main__.py
papyrus_scripts/cli.py
papyrus_scripts/download.py
papyrus_scripts/fingerprint.py
papyrus_scripts/matchRCSB.py
papyrus_scripts/modelling.py
papyrus_scripts/neuralnet.py
papyrus_scripts/oop.py
papyrus_scripts/preprocess.py
papyrus_scripts/reader.py
papyrus_scripts/subsim_search.py
papyrus_scripts/utils/IO.py
papyrus_scripts/utils/UniprotMatch.py
papyrus_scripts/utils/__init__.py
papyrus_scripts/utils/aliases.json
papyrus_scripts/utils/links.json
papyrus_scripts/utils/mol_reader.py
papyrus_scripts-2.1.2.dist-info/licenses/LICENSE
papyrus_scripts-2.1.2.dist-info/METADATA
papyrus_scripts-2.1.2.dist-info/WHEEL
papyrus_scripts-2.1.2.dist-info/entry_points.txt
papyrus_scripts-2.1.2.dist-info/top_level.txt
papyrus_scripts-2.1.2.dist-info/RECORD
