Metadata-Version: 2.4
Name: papyrus_scripts
Version: 2.1.2
Summary: A collection of scripts to handle the Papyrus bioactivity dataset
Home-page: https://github.com/OlivierBeq/Papyrus-scripts
Author: Olivier J. M. Béquignon - Brandon J. Bongers - Willem Jespers
Author-email: "olivier.bequignon.maintainer@gmail.com"
Maintainer: Olivier J. M. Béquignon
Maintainer-email: "olivier.bequignon.maintainer@gmail.com"
Keywords: bioactivity data,QSAR,proteochemometrics,cheminformatics,modelling,machine learning
Classifier: Development Status :: 2 - Pre-Alpha
Classifier: Programming Language :: Python
Classifier: Programming Language :: Python :: 3.10
Classifier: Programming Language :: Python :: 3.9
Classifier: Programming Language :: Python :: 3.8
Classifier: Programming Language :: Python :: 3.7
Classifier: Programming Language :: Python :: 3.6
License-File: LICENSE
Requires-Dist: numpy>=2.0.0
Requires-Dist: pandas
Requires-Dist: rdkit
Requires-Dist: requests
Requires-Dist: joblib
Requires-Dist: tqdm
Requires-Dist: mordred
Requires-Dist: swifter
Requires-Dist: scikit-learn
Requires-Dist: xgboost
Requires-Dist: pystow
Requires-Dist: prodec
Provides-Extra: docs
Requires-Dist: sphinx; extra == "docs"
Requires-Dist: sphinx-rtd-theme; extra == "docs"
Requires-Dist: sphinx-autodoc-typehints; extra == "docs"
Provides-Extra: testing
Requires-Dist: pytest; extra == "testing"
Requires-Dist: parameterized; extra == "testing"
Dynamic: license-file
